flat_data/__init__.py
flat_data/flat_data.py
flat_data-1.0.1.dist-info/LICENSE.md
flat_data-1.0.1.dist-info/METADATA
flat_data-1.0.1.dist-info/WHEEL
flat_data-1.0.1.dist-info/top_level.txt
flat_data-1.0.1.dist-info/RECORD
