Metadata-Version: 2.1
Name: flat_data
Version: 1.0.1
Summary: A Python library which provides a seamless solution for converting unstructured data into structured format, making data easier to process, analyze, and store. By organizing nested or inconsistent data into a standardized format, this library simplifies data handling for various applications.
Home-page: https://github.com/rohan-raut/flat-data
Author: Rohan Raut
License-File: LICENSE.md
